[{"kind": "Listing", "data": {"after": null, "dist": 1, "modhash": "", "geo_filter": "", "children": [{"kind": "t3", "data": {"approved_at_utc": null, "subreddit": "RoFiscalitate2", "selftext": "Salut\u0103ri! M\u0103 confrunt azi cu o situa\u021bie ciudat\u0103 \u0219i a\u0219 avea nevoie de ceva sfaturi, m\u0103car pentru lini\u0219tea mea (luni merg la ANAF sa vb cu ei).\n\nSitua\u021bia e urm\u0103toarea: Subsemnatul PF, toate impozite, taxe pl\u0103tite. Urmeaz\u0103 s\u0103 fac nunta in august pentru care pl\u0103tesc factur\u0103 avans 2000ron contravaloare servicii foto+video unei firme X. (Contractul este de 10000 cu plata dup\u0103 nunt\u0103).\n\nPrimesc azi notificare de la ANAF, pe SPV, ca am poprire (2 de fapt, cu aceea\u0219i firm\u0103) in valoare de 23000 lei adunate, cu sume datorate firmei X. Bine\u00een\u021beles c\u0103 l-am sunat pe individul care reprezint\u0103 firma X, a spus c\u0103 a\u0219a procedeaz\u0103 la to\u021bi clien\u021bii, c\u0103 lucreaz\u0103 cu facturi \u0219i posibil sa fie gre\u0219eal\u0103. \nCu toate astea, ce pot face? De ce primesc eu client, PF de plata la o societate comerciala, prin ANAF pentru un contract de prest\u0103ri servicii? Exist\u0103 posibilitatea ca s\u0103 m\u0103 oblige cumva ANAF sa pl\u0103tesc/executat silit?\n\nSunt total pe l\u00e2ng\u0103 acest domeniu contabil, cred c\u0103 se observa. Mul\u021bumesc!", "user_reports": [], "saved": false, "mod_reason_title": null, "gilded": 0, "clicked": false, "title": "Poprire - what?!?", "link_flair_richtext": [], "subreddit_name_prefixed": "r/RoFiscalitate2", "hidden": false, "pwls": 6, "link_flair_css_class": null, "downs": 0, "thumbnail_height": null, "top_awarded_type": null, "hide_score": false, "name": "t3_1t10351", "quarantine": false, "link_flair_text_color": "dark", "upvote_ratio": 0.88, "author_flair_background_color": null, "subreddit_type": "public", "ups": 40, "total_awards_received": 0, "media_embed": {}, "thumbnail_width": null, "author_flair_template_id": null, "is_original_content": false, "author_fullname": "t2_3pw5u8ng", "secure_media": null, "is_reddit_media_domain": false, "is_meta": false, "category": null, "secure_media_embed": {}, "link_flair_text": null, "can_mod_post": false, "score": 40, "approved_by": null, "is_created_from_ads_ui": false, "author_premium": false, "thumbnail": "self", "edited": false, "author_flair_css_class": null, "author_flair_richtext": [], "gildings": {}, "content_categories": null, "is_self": true, "mod_note": null, "created": 1777656677.0, "link_flair_type": "text", "wls": 6, "removed_by_category": null, "banned_by": null, "author_flair_type": "text", "domain": "self.RoFiscalitate2", "allow_live_comments": false, "selftext_html": "&lt;!-- SC_OFF --&gt;&lt;div class=\"md\"&gt;&lt;p&gt;Salut\u0103ri! M\u0103 confrunt azi cu o situa\u021bie ciudat\u0103 \u0219i a\u0219 avea nevoie de ceva sfaturi, m\u0103car pentru lini\u0219tea mea (luni merg la ANAF sa vb cu ei).&lt;/p&gt;\n\n&lt;p&gt;Situa\u021bia e urm\u0103toarea: Subsemnatul PF, toate impozite, taxe pl\u0103tite. Urmeaz\u0103 s\u0103 fac nunta in august pentru care pl\u0103tesc factur\u0103 avans 2000ron contravaloare servicii foto+video unei firme X. (Contractul este de 10000 cu plata dup\u0103 nunt\u0103).&lt;/p&gt;\n\n&lt;p&gt;Primesc azi notificare de la ANAF, pe SPV, ca am poprire (2 de fapt, cu aceea\u0219i firm\u0103) in valoare de 23000 lei adunate, cu sume datorate firmei X. Bine\u00een\u021beles c\u0103 l-am sunat pe individul care reprezint\u0103 firma X, a spus c\u0103 a\u0219a procedeaz\u0103 la to\u021bi clien\u021bii, c\u0103 lucreaz\u0103 cu facturi \u0219i posibil sa fie gre\u0219eal\u0103. \nCu toate astea, ce pot face? De ce primesc eu client, PF de plata la o societate comerciala, prin ANAF pentru un contract de prest\u0103ri servicii? Exist\u0103 posibilitatea ca s\u0103 m\u0103 oblige cumva ANAF sa pl\u0103tesc/executat silit?&lt;/p&gt;\n\n&lt;p&gt;Sunt total pe l\u00e2ng\u0103 acest domeniu contabil, cred c\u0103 se observa. Mul\u021bumesc!&lt;/p&gt;\n&lt;/div&gt;&lt;!-- SC_ON --&gt;", "likes": null, "suggested_sort": null, "banned_at_utc": null, "view_count": null, "archived": false, "no_follow": false, "is_crosspostable": false, "pinned": false, "over_18": false, "all_awardings": [], "awarders": [], "media_only": false, "can_gild": false, "spoiler": false, "locked": false, "author_flair_text": null, "treatment_tags": [], "visited": false, "removed_by": null, "num_reports": null, "distinguished": null, "subreddit_id": "t5_ap8imo", "author_is_blocked": false, "mod_reason_by": null, "removal_reason": null, "link_flair_background_color": "", "id": "1t10351", "is_robot_indexable": true, "num_duplicates": 0, "report_reasons": null, "author": "GabryelPH", "discussion_type": null, "num_comments": 30, "send_replies": true, "media": null, "contest_mode": false, "author_patreon_flair": false, "author_flair_text_color": null, "permalink": "/r/RoFiscalitate2/comments/1t10351/poprire_what/", "stickied": false, "url": "https://www.reddit.com/r/RoFiscalitate2/comments/1t10351/poprire_what/", "subreddit_subscribers": 15215, "created_utc": 1777656677.0, "num_crossposts": 0, "mod_reports": [], "is_video": false}}], "before": null}}, {"kind": "Listing", "data": {"after": null, "dist": null, "modhash": "", "geo_filter": "", "children": [{"kind": "t1", "data": {"subreddit_id": "t5_ap8imo", "approved_at_utc": null, "author_is_blocked": false, "comment_type": null, "awarders": [], "mod_reason_by": null, "banned_by": null, "author_flair_type": "text", "total_awards_received": 0, "subreddit": "RoFiscalitate2", "author_flair_template_id": null, "likes": null, "replies": "", "user_reports": [], "saved": false, "id": "ojd13zf", "banned_at_utc": null, "mod_reason_title": null, "gilded": 0, "archived": false, "collapsed_reason_code": null, "no_follow": false, "author": "Tatauless", "can_mod_post": false, "created_utc": 1777658498.0, "send_replies": true, "parent_id": "t3_1t10351", "score": 59, "author_fullname": "t2_frj31kx", "approved_by": null, "mod_note": null, "all_awardings": [], "collapsed": false, "body": "Esti ter\u021b poprit, nu ai tu poprire pe contul tau bancar. Te \u00een\u0219tiin\u021beaz\u0103 ca daca ai sa ii dai bani debitorului sa ii dai statului.\n\nEdit: ANAF face datornicii de ru\u0219ine in fata clien\u021bilor", "edited": false, "top_awarded_type": null, "author_flair_css_class": null, "name": "t1_ojd13zf", "is_submitter": false, "downs": 0, "author_flair_richtext": [], "author_patreon_flair": false, "body_html": "&lt;div class=\"md\"&gt;&lt;p&gt;Esti ter\u021b poprit, nu ai tu poprire pe contul tau bancar. Te \u00een\u0219tiin\u021beaz\u0103 ca daca ai sa ii dai bani debitorului sa ii dai statului.&lt;/p&gt;\n\n&lt;p&gt;Edit: ANAF face datornicii de ru\u0219ine in fata clien\u021bilor&lt;/p&gt;\n&lt;/div&gt;", "removal_reason": null, "collapsed_reason": null, "distinguished": null, "associated_award": null, "stickied": false, "author_premium": false, "can_gild": false, "gildings": {}, "unrepliable_reason": null, "author_flair_text_color": null, "score_hidden": false, "permalink": "/r/RoFiscalitate2/comments/1t10351/poprire_what/ojd13zf/", "subreddit_type": "public", "locked": false, "report_reasons": null, "created": 1777658498.0, "author_flair_text": null, "treatment_tags": [], "link_id": "t3_1t10351", "subreddit_name_prefixed": "r/RoFiscalitate2", "controversiality": 0, "depth": 0, "author_flair_background_color": null, "collapsed_because_crowd_control": null, "mod_reports": [], "num_reports": null, "ups": 59}}, {"kind": "t1", "data": {"subreddit_id": "t5_ap8imo", "approved_at_utc": null, "author_is_blocked": false, "comment_type": null, "awarders": [], "mod_reason_by": null, "banned_by": null, "author_flair_type": "text", "total_awards_received": 0, "subreddit": "RoFiscalitate2", "author_flair_template_id": null, "likes": null, "replies": "", "user_reports": [], "saved": false, "id": "ojcvvpw", "banned_at_utc": null, "mod_reason_title": null, "gilded": 0, "archived": false, "collapsed_reason_code": null, "no_follow": false, "author": "SalamanderVast3861", "can_mod_post": false, "created_utc": 1777657086.0, "send_replies": true, "parent_id": "t3_1t10351", "score": 11, "author_fullname": "t2_rqx0a3brk", "approved_by": null, "mod_note": null, "all_awardings": [], "collapsed": false, "body": "Cand o firma are datorii, ANAF poate lua banii de la clien\u021bii s\u0103i care nu \u0219i-au achitat facturile \u00een termenul de pe factura. Vezi ce contract, factura \u021bi s-a emis. Oricum, pe asta o l\u0103mure\u0219ti cu ANAF.   Gre\u0219eal\u0103 sau nu, firma cu siguran\u021b\u0103 trebuie s\u0103 \u00ee\u0219i corecteze ni\u0219te lucuri pe acolo.  La cum se comport\u0103 \u0103\u0219tia din domeniul \u0103sta, sunt toate \u0219ansele ca suma s\u0103 fie corect\u0103 :)) ", "edited": false, "top_awarded_type": null, "author_flair_css_class": null, "name": "t1_ojcvvpw", "is_submitter": false, "downs": 0, "author_flair_richtext": [], "author_patreon_flair": false, "body_html": "&lt;div class=\"md\"&gt;&lt;p&gt;Cand o firma are datorii, ANAF poate lua banii de la clien\u021bii s\u0103i care nu \u0219i-au achitat facturile \u00een termenul de pe factura. Vezi ce contract, factura \u021bi s-a emis. Oricum, pe asta o l\u0103mure\u0219ti cu ANAF.   Gre\u0219eal\u0103 sau nu, firma cu siguran\u021b\u0103 trebuie s\u0103 \u00ee\u0219i corecteze ni\u0219te lucuri pe acolo.  La cum se comport\u0103 \u0103\u0219tia din domeniul \u0103sta, sunt toate \u0219ansele ca suma s\u0103 fie corect\u0103 :)) &lt;/p&gt;\n&lt;/div&gt;", "removal_reason": null, "collapsed_reason": null, "distinguished": null, "associated_award": null, "stickied": false, "author_premium": false, "can_gild": false, "gildings": {}, "unrepliable_reason": null, "author_flair_text_color": null, "score_hidden": false, "permalink": "/r/RoFiscalitate2/comments/1t10351/poprire_what/ojcvvpw/", "subreddit_type": "public", "locked": false, "report_reasons": null, "created": 1777657086.0, "author_flair_text": null, "treatment_tags": [], "link_id": "t3_1t10351", "subreddit_name_prefixed": "r/RoFiscalitate2", "controversiality": 0, "depth": 0, "author_flair_background_color": null, "collapsed_because_crowd_control": null, "mod_reports": [], "num_reports": null, "ups": 11}}, {"kind": "t1", "data": {"subreddit_id": "t5_ap8imo", "approved_at_utc": null, "author_is_blocked": false, "comment_type": null, "awarders": [], "mod_reason_by": null, "banned_by": null, "author_flair_type": "text", "total_awards_received": 0, "subreddit": "RoFiscalitate2", "author_flair_template_id": null, "likes": null, "replies": {"kind": "Listing", "data": {"after": null, "dist": null, "modhash": "", "geo_filter": "", "children": [{"kind": "t1", "data": {"subreddit_id": "t5_ap8imo", "approved_at_utc": null, "author_is_blocked": false, "comment_type": null, "awarders": [], "mod_reason_by": null, "banned_by": null, "author_flair_type": "text", "total_awards_received": 0, "subreddit": "RoFiscalitate2", "author_flair_template_id": null, "likes": null, "replies": {"kind": "Listing", "data": {"after": null, "dist": null, "modhash": "", "geo_filter": "", "children": [{"kind": "t1", "data": {"subreddit_id": "t5_ap8imo", "approved_at_utc": null, "author_is_blocked": false, "comment_type": null, "awarders": [], "mod_reason_by": null, "banned_by": null, "author_flair_type": "text", "total_awards_received": 0, "subreddit": "RoFiscalitate2", "author_flair_template_id": null, "likes": null, "replies": {"kind": "Listing", "data": {"after": null, "dist": null, "modhash": "", "geo_filter": "", "children": [{"kind": "t1", "data": {"subreddit_id": "t5_ap8imo", "approved_at_utc": null, "author_is_blocked": false, "comment_type": null, "awarders": [], "mod_reason_by": null, "banned_by": null, "author_flair_type": "text", "total_awards_received": 0, "subreddit": "RoFiscalitate2", "author_flair_template_id": null, "likes": null, "replies": "", "user_reports": [], "saved": false, "id": "ojhl6s0", "banned_at_utc": null, "mod_reason_title": null, "gilded": 0, "archived": false, "collapsed_reason_code": null, "no_follow": true, "author": "manu144x", "can_mod_post": false, "send_replies": true, "parent_id": "t1_ojhj037", "score": 1, "author_fullname": "t2_eec62uo", "removal_reason": null, "approved_by": null, "mod_note": null, "all_awardings": [], "collapsed": false, "body": "Dac\u0103 datoria e considerat\u0103 executorie atunci anaf are dreptul s\u0103 te popreasc\u0103. \n\nDac\u0103 nu este, atunci da, te roag\u0103 frumos ca pe viitor s\u0103 achi\u021bi lor nu la furnizor. ", "edited": false, "top_awarded_type": null, "author_flair_css_class": null, "name": "t1_ojhl6s0", "is_submitter": false, "downs": 0, "author_flair_richtext": [], "author_patreon_flair": false, "body_html": "&lt;div class=\"md\"&gt;&lt;p&gt;Dac\u0103 datoria e considerat\u0103 executorie atunci anaf are dreptul s\u0103 te popreasc\u0103. &lt;/p&gt;\n\n&lt;p&gt;Dac\u0103 nu este, atunci da, te roag\u0103 frumos ca pe viitor s\u0103 achi\u021bi lor nu la furnizor. &lt;/p&gt;\n&lt;/div&gt;", "gildings": {}, "collapsed_reason": null, "distinguished": null, "associated_award": null, "stickied": false, "author_premium": false, "can_gild": false, "link_id": "t3_1t10351", "unrepliable_reason": null, "author_flair_text_color": null, "score_hidden": false, "permalink": "/r/RoFiscalitate2/comments/1t10351/poprire_what/ojhl6s0/", "subreddit_type": "public", "locked": false, "report_reasons": null, "created": 1777722310.0, "author_flair_text": null, "treatment_tags": [], "created_utc": 1777722310.0, "subreddit_name_prefixed": "r/RoFiscalitate2", "controversiality": 0, "depth": 3, "author_flair_background_color": null, "collapsed_because_crowd_control": null, "mod_reports": [], "num_reports": null, "ups": 1}}], "before": null}}, "user_reports": [], "saved": false, "id": "ojhj037", "banned_at_utc": null, "mod_reason_title": null, "gilded": 0, "archived": false, "collapsed_reason_code": null, "no_follow": false, "author": "harubax", "can_mod_post": false, "send_replies": true, "parent_id": "t1_ojd79s2", "score": 4, "author_fullname": "t2_12z3rh", "removal_reason": null, "approved_by": null, "mod_note": null, "all_awardings": [], "body": "ANAF solicit\u0103 s\u0103 virezi \u00een conturile Trezoreriei sumele datorate societ\u0103\u021bii. Firma nu se afl\u0103 nici \u00een insolven\u021b\u0103 nici \u00een faliment.", "edited": false, "top_awarded_type": null, "downs": 0, "author_flair_css_class": null, "name": "t1_ojhj037", "is_submitter": false, "collapsed": false, "author_flair_richtext": [], "author_patreon_flair": false, "body_html": "&lt;div class=\"md\"&gt;&lt;p&gt;ANAF solicit\u0103 s\u0103 virezi \u00een conturile Trezoreriei sumele datorate societ\u0103\u021bii. Firma nu se afl\u0103 nici \u00een insolven\u021b\u0103 nici \u00een faliment.&lt;/p&gt;\n&lt;/div&gt;", "gildings": {}, "collapsed_reason": null, "distinguished": null, "associated_award": null, "stickied": false, "author_premium": false, "can_gild": false, "link_id": "t3_1t10351", "unrepliable_reason": null, "author_flair_text_color": null, "score_hidden": false, "permalink": "/r/RoFiscalitate2/comments/1t10351/poprire_what/ojhj037/", "subreddit_type": "public", "locked": false, "report_reasons": null, "created": 1777721373.0, "author_flair_text": null, "treatment_tags": [], "created_utc": 1777721373.0, "subreddit_name_prefixed": "r/RoFiscalitate2", "controversiality": 0, "depth": 2, "author_flair_background_color": null, "collapsed_because_crowd_control": null, "mod_reports": [], "num_reports": null, "ups": 4}}, {"kind": "t1", "data": {"subreddit_id": "t5_ap8imo", "approved_at_utc": null, "author_is_blocked": false, "comment_type": null, "awarders": [], "mod_reason_by": null, "banned_by": null, "author_flair_type": "text", "total_awards_received": 0, "subreddit": "RoFiscalitate2", "author_flair_template_id": null, "likes": null, "replies": {"kind": "Listing", "data": {"after": null, "dist": null, "modhash": "", "geo_filter": "", "children": [{"kind": "t1", "data": {"subreddit_id": "t5_ap8imo", "approved_at_utc": null, "author_is_blocked": false, "comment_type": null, "awarders": [], "mod_reason_by": null, "banned_by": null, "author_flair_type": "text", "total_awards_received": 0, "subreddit": "RoFiscalitate2", "author_flair_template_id": null, "likes": null, "replies": "", "user_reports": [], "saved": false, "id": "ojdzsoq", "banned_at_utc": null, "mod_reason_title": null, "gilded": 0, "archived": false, "collapsed_reason_code": null, "no_follow": false, "author": "moneydies", "can_mod_post": false, "send_replies": true, "parent_id": "t1_ojdj2lb", "score": 6, "author_fullname": "t2_b4avl", "removal_reason": null, "approved_by": null, "mod_note": null, "all_awardings": [], "collapsed": false, "body": "Chiar nu functioneaza asa.", "edited": false, "top_awarded_type": null, "author_flair_css_class": null, "name": "t1_ojdzsoq", "is_submitter": false, "downs": 0, "author_flair_richtext": [], "author_patreon_flair": false, "body_html": "&lt;div class=\"md\"&gt;&lt;p&gt;Chiar nu functioneaza asa.&lt;/p&gt;\n&lt;/div&gt;", "gildings": {}, "collapsed_reason": null, "distinguished": null, "associated_award": null, "stickied": false, "author_premium": false, "can_gild": false, "link_id": "t3_1t10351", "unrepliable_reason": null, "author_flair_text_color": null, "score_hidden": false, "permalink": "/r/RoFiscalitate2/comments/1t10351/poprire_what/ojdzsoq/", "subreddit_type": "public", "locked": false, "report_reasons": null, "created": 1777668468.0, "author_flair_text": null, "treatment_tags": [], "created_utc": 1777668468.0, "subreddit_name_prefixed": "r/RoFiscalitate2", "controversiality": 0, "depth": 3, "author_flair_background_color": null, "collapsed_because_crowd_control": null, "mod_reports": [], "num_reports": null, "ups": 6}}], "before": null}}, "user_reports": [], "saved": false, "id": "ojdj2lb", "banned_at_utc": null, "mod_reason_title": null, "gilded": 0, "archived": false, "collapsed_reason_code": null, "no_follow": true, "author": "Mmiron0824", "can_mod_post": false, "send_replies": true, "parent_id": "t1_ojd79s2", "score": 0, "author_fullname": "t2_622cq7p9", "removal_reason": null, "approved_by": null, "mod_note": null, "all_awardings": [], "body": "Nu func\u021bioneaz\u0103 a\u0219a", "edited": false, "top_awarded_type": null, "downs": 0, "author_flair_css_class": null, "name": "t1_ojdj2lb", "is_submitter": false, "collapsed": false, "author_flair_richtext": [], "author_patreon_flair": false, "body_html": "&lt;div class=\"md\"&gt;&lt;p&gt;Nu func\u021bioneaz\u0103 a\u0219a&lt;/p&gt;\n&lt;/div&gt;", "gildings": {}, "collapsed_reason": null, "distinguished": null, "associated_award": null, "stickied": false, "author_premium": false, "can_gild": false, "link_id": "t3_1t10351", "unrepliable_reason": null, "author_flair_text_color": null, "score_hidden": false, "permalink": "/r/RoFiscalitate2/comments/1t10351/poprire_what/ojdj2lb/", "subreddit_type": "public", "locked": false, "report_reasons": null, "created": 1777663615.0, "author_flair_text": null, "treatment_tags": [], "created_utc": 1777663615.0, "subreddit_name_prefixed": "r/RoFiscalitate2", "controversiality": 0, "depth": 2, "author_flair_background_color": null, "collapsed_because_crowd_control": null, "mod_reports": [], "num_reports": null, "ups": 0}}], "before": null}}, "user_reports": [], "saved": false, "id": "ojd79s2", "banned_at_utc": null, "mod_reason_title": null, "gilded": 0, "archived": false, "collapsed_reason_code": null, "no_follow": false, "author": "manu144x", "can_mod_post": false, "created_utc": 1777660237.0, "send_replies": true, "parent_id": "t1_ojcwf3v", "score": 4, "author_fullname": "t2_eec62uo", "removal_reason": null, "approved_by": null, "mod_note": null, "all_awardings": [], "body": "Este pe contul lui.\n\nSun\u0103 ridicol dar a\u0219a func\u021bioneaz\u0103 procesul. Dac\u0103 firma aia a declarat c\u0103 OP \u00eei datoreaz\u0103 bani (prin contract) ANAF poate popri contul clientului \u0219i TU trebuie s\u0103 mergi s\u0103 conte\u0219ti treaba.\n\nE super abuziv\u0103 dar a\u0219a func\u021bioneaz\u0103 procedura.\n\nEi consider\u0103 datoria executorie \u0219i se comport\u0103 cu un executor \u00een contextul firmei care probabil e \u00een insolven\u021b\u0103 sau faliment.", "edited": false, "top_awarded_type": null, "author_flair_css_class": null, "name": "t1_ojd79s2", "is_submitter": false, "downs": 0, "author_flair_richtext": [], "author_patreon_flair": false, "body_html": "&lt;div class=\"md\"&gt;&lt;p&gt;Este pe contul lui.&lt;/p&gt;\n\n&lt;p&gt;Sun\u0103 ridicol dar a\u0219a func\u021bioneaz\u0103 procesul. Dac\u0103 firma aia a declarat c\u0103 OP \u00eei datoreaz\u0103 bani (prin contract) ANAF poate popri contul clientului \u0219i TU trebuie s\u0103 mergi s\u0103 conte\u0219ti treaba.&lt;/p&gt;\n\n&lt;p&gt;E super abuziv\u0103 dar a\u0219a func\u021bioneaz\u0103 procedura.&lt;/p&gt;\n\n&lt;p&gt;Ei consider\u0103 datoria executorie \u0219i se comport\u0103 cu un executor \u00een contextul firmei care probabil e \u00een insolven\u021b\u0103 sau faliment.&lt;/p&gt;\n&lt;/div&gt;", "gildings": {}, "collapsed_reason": null, "distinguished": null, "associated_award": null, "stickied": false, "author_premium": false, "can_gild": false, "link_id": "t3_1t10351", "unrepliable_reason": null, "author_flair_text_color": null, "score_hidden": false, "permalink": "/r/RoFiscalitate2/comments/1t10351/poprire_what/ojd79s2/", "subreddit_type": "public", "locked": false, "report_reasons": null, "created": 1777660237.0, "author_flair_text": null, "treatment_tags": [], "collapsed": false, "subreddit_name_prefixed": "r/RoFiscalitate2", "controversiality": 1, "depth": 1, "author_flair_background_color": null, "collapsed_because_crowd_control": null, "mod_reports": [], "num_reports": null, "ups": 4}}], "before": null}}, "user_reports": [], "saved": false, "id": "ojcwf3v", "banned_at_utc": null, "mod_reason_title": null, "gilded": 0, "archived": false, "collapsed_reason_code": null, "no_follow": false, "author": "moneydies", "can_mod_post": false, "created_utc": 1777657231.0, "send_replies": true, "parent_id": "t3_1t10351", "score": 28, "author_fullname": "t2_b4avl", "approved_by": null, "mod_note": null, "all_awardings": [], "collapsed": false, "body": "Dragule, te rog citeste foarte atent acel document.  \nDaca era poprire pe contul tau, iti trimitea si banca un mesaj.  \nDin ce zici tu, pare sa fie poprire pentru sune datorate de catre terti.  \nDeschide pdf ul ala de la anaf si citeste-l cu atentie", "edited": false, "top_awarded_type": null, "author_flair_css_class": null, "name": "t1_ojcwf3v", "is_submitter": false, "downs": 0, "author_flair_richtext": [], "author_patreon_flair": false, "body_html": "&lt;div class=\"md\"&gt;&lt;p&gt;Dragule, te rog citeste foarte atent acel document.&lt;br/&gt;\nDaca era poprire pe contul tau, iti trimitea si banca un mesaj.&lt;br/&gt;\nDin ce zici tu, pare sa fie poprire pentru sune datorate de catre terti.&lt;br/&gt;\nDeschide pdf ul ala de la anaf si citeste-l cu atentie&lt;/p&gt;\n&lt;/div&gt;", "removal_reason": null, "collapsed_reason": null, "distinguished": null, "associated_award": null, "stickied": false, "author_premium": false, "can_gild": false, "gildings": {}, "unrepliable_reason": null, "author_flair_text_color": null, "score_hidden": false, "permalink": "/r/RoFiscalitate2/comments/1t10351/poprire_what/ojcwf3v/", "subreddit_type": "public", "locked": false, "report_reasons": null, "created": 1777657231.0, "author_flair_text": null, "treatment_tags": [], "link_id": "t3_1t10351", "subreddit_name_prefixed": "r/RoFiscalitate2", "controversiality": 0, "depth": 0, "author_flair_background_color": null, "collapsed_because_crowd_control": null, "mod_reports": [], "num_reports": null, "ups": 28}}, {"kind": "t1", "data": {"subreddit_id": "t5_ap8imo", "approved_at_utc": null, "author_is_blocked": false, "comment_type": null, "awarders": [], "mod_reason_by": null, "banned_by": null, "author_flair_type": "text", "total_awards_received": 0, "subreddit": "RoFiscalitate2", "author_flair_template_id": null, "likes": null, "replies": {"kind": "Listing", "data": {"after": null, "dist": null, "modhash": "", "geo_filter": "", "children": [{"kind": "t1", "data": {"subreddit_id": "t5_ap8imo", "approved_at_utc": null, "author_is_blocked": false, "comment_type": null, "awarders": [], "mod_reason_by": null, "banned_by": null, "author_flair_type": "text", "total_awards_received": 0, "subreddit": "RoFiscalitate2", "author_flair_template_id": null, "likes": null, "replies": {"kind": "Listing", "data": {"after": null, "dist": null, "modhash": "", "geo_filter": "", "children": [{"kind": "t1", "data": {"subreddit_id": "t5_ap8imo", "approved_at_utc": null, "author_is_blocked": false, "comment_type": null, "awarders": [], "mod_reason_by": null, "banned_by": null, "author_flair_type": "text", "total_awards_received": 0, "subreddit": "RoFiscalitate2", "author_flair_template_id": null, "likes": null, "replies": {"kind": "Listing", "data": {"after": null, "dist": null, "modhash": "", "geo_filter": "", "children": [{"kind": "t1", "data": {"subreddit_id": "t5_ap8imo", "approved_at_utc": null, "author_is_blocked": false, "comment_type": null, "awarders": [], "mod_reason_by": null, "banned_by": null, "author_flair_type": "text", "total_awards_received": 0, "subreddit": "RoFiscalitate2", "author_flair_template_id": null, "likes": null, "replies": {"kind": "Listing", "data": {"after": null, "dist": null, "modhash": "", "geo_filter": "", "children": [{"kind": "t1", "data": {"subreddit_id": "t5_ap8imo", "approved_at_utc": null, "author_is_blocked": false, "comment_type": null, "awarders": [], "mod_reason_by": null, "banned_by": null, "author_flair_type": "text", "total_awards_received": 0, "subreddit": "RoFiscalitate2", "author_flair_template_id": null, "distinguished": null, "likes": null, "replies": "", "user_reports": [], "saved": false, "id": "ojh34vd", "banned_at_utc": null, "mod_reason_title": null, "gilded": 0, "archived": false, "collapsed_reason_code": null, "no_follow": false, "author": "GabryelPH", "can_mod_post": false, "send_replies": true, "parent_id": "t1_ojgy35a", "score": 4, "author_fullname": "t2_3pw5u8ng", "removal_reason": null, "approved_by": null, "mod_note": null, "all_awardings": [], "body": "In cel mai r\u0103u caz, anulez contractul si s\u0103 v\u0103d cum mai cer respectivii bani. \u0218i uite cum \u00eencurajeaz\u0103 dragii no\u0219tri legiuitori munca la negru.", "edited": false, "author_flair_css_class": null, "name": "t1_ojh34vd", "is_submitter": true, "downs": 0, "author_flair_richtext": [], "author_patreon_flair": false, "body_html": "&lt;div class=\"md\"&gt;&lt;p&gt;In cel mai r\u0103u caz, anulez contractul si s\u0103 v\u0103d cum mai cer respectivii bani. \u0218i uite cum \u00eencurajeaz\u0103 dragii no\u0219tri legiuitori munca la negru.&lt;/p&gt;\n&lt;/div&gt;", "gildings": {}, "collapsed_reason": null, "link_id": "t3_1t10351", "associated_award": null, "stickied": false, "author_premium": false, "can_gild": false, "top_awarded_type": null, "unrepliable_reason": null, "author_flair_text_color": null, "treatment_tags": [], "score_hidden": false, "permalink": "/r/RoFiscalitate2/comments/1t10351/poprire_what/ojh34vd/", "subreddit_type": "public", "locked": false, "report_reasons": null, "created": 1777713344.0, "author_flair_text": null, "collapsed": false, "created_utc": 1777713344.0, "subreddit_name_prefixed": "r/RoFiscalitate2", "controversiality": 0, "depth": 4, "author_flair_background_color": null, "collapsed_because_crowd_control": null, "mod_reports": [], "num_reports": null, "ups": 4}}], "before": null}}, "user_reports": [], "saved": false, "id": "ojgy35a", "banned_at_utc": null, "mod_reason_title": null, "gilded": 0, "archived": false, "collapsed_reason_code": null, "no_follow": true, "author": "Secure-Scratch8910", "can_mod_post": false, "send_replies": true, "parent_id": "t1_ojgx0rr", "score": 3, "author_fullname": "t2_4txwm56u", "removal_reason": null, "approved_by": null, "mod_note": null, "all_awardings": [], "collapsed": false, "body": "S\u0103 nu fii dezam\u0103git dac\u0103 r\u0103spunsul nu va fi cel pe care \u00eel a\u0219tep\u021bi; asta e \u021bara \u00een care tr\u0103im. De exemplu, anul acesta am v\u00e2ndut o ma\u0219in\u0103, iar cump\u0103r\u0103torul nu avea impozitele pl\u0103tite pe 2025 av\u00e2nd \u00een vedere c\u0103 tranzac\u021bia a fost f\u0103cut\u0103 \u00een februarie. A trebuit s\u0103 mearg\u0103 s\u0103-\u0219i pl\u0103teasc\u0103 impozitele restante ca s\u0103 \u00eei pot da fiscalul. Altfel, era imposibil s\u0103 facem trecerea de pe numele meu pe al lui.", "edited": false, "top_awarded_type": null, "author_flair_css_class": null, "name": "t1_ojgy35a", "is_submitter": false, "downs": 0, "author_flair_richtext": [], "author_patreon_flair": false, "body_html": "&lt;div class=\"md\"&gt;&lt;p&gt;S\u0103 nu fii dezam\u0103git dac\u0103 r\u0103spunsul nu va fi cel pe care \u00eel a\u0219tep\u021bi; asta e \u021bara \u00een care tr\u0103im. De exemplu, anul acesta am v\u00e2ndut o ma\u0219in\u0103, iar cump\u0103r\u0103torul nu avea impozitele pl\u0103tite pe 2025 av\u00e2nd \u00een vedere c\u0103 tranzac\u021bia a fost f\u0103cut\u0103 \u00een februarie. A trebuit s\u0103 mearg\u0103 s\u0103-\u0219i pl\u0103teasc\u0103 impozitele restante ca s\u0103 \u00eei pot da fiscalul. Altfel, era imposibil s\u0103 facem trecerea de pe numele meu pe al lui.&lt;/p&gt;\n&lt;/div&gt;", "gildings": {}, "collapsed_reason": null, "distinguished": null, "associated_award": null, "stickied": false, "author_premium": false, "can_gild": false, "link_id": "t3_1t10351", "unrepliable_reason": null, "author_flair_text_color": null, "score_hidden": false, "permalink": "/r/RoFiscalitate2/comments/1t10351/poprire_what/ojgy35a/", "subreddit_type": "public", "locked": false, "report_reasons": null, "created": 1777710560.0, "author_flair_text": null, "treatment_tags": [], "created_utc": 1777710560.0, "subreddit_name_prefixed": "r/RoFiscalitate2", "controversiality": 0, "depth": 3, "author_flair_background_color": null, "collapsed_because_crowd_control": null, "mod_reports": [], "num_reports": null, "ups": 3}}, {"kind": "t1", "data": {"subreddit_id": "t5_ap8imo", "approved_at_utc": null, "author_is_blocked": false, "comment_type": null, "awarders": [], "mod_reason_by": null, "banned_by": null, "author_flair_type": "text", "total_awards_received": 0, "subreddit": "RoFiscalitate2", "author_flair_template_id": null, "likes": null, "replies": "", "user_reports": [], "saved": false, "id": "ok0ryp8", "banned_at_utc": null, "mod_reason_title": null, "gilded": 0, "archived": false, "collapsed_reason_code": null, "no_follow": true, "author": "savornicesei", "can_mod_post": false, "send_replies": true, "parent_id": "t1_ojgx0rr", "score": 1, "author_fullname": "t2_4hqfy43y", "removal_reason": null, "approved_by": null, "mod_note": null, "all_awardings": [], "collapsed": false, "body": "Ai fi surprins.", "edited": false, "top_awarded_type": null, "author_flair_css_class": null, "name": "t1_ok0ryp8", "is_submitter": false, "downs": 0, "author_flair_richtext": [], "author_patreon_flair": false, "body_html": "&lt;div class=\"md\"&gt;&lt;p&gt;Ai fi surprins.&lt;/p&gt;\n&lt;/div&gt;", "gildings": {}, "collapsed_reason": null, "distinguished": null, "associated_award": null, "stickied": false, "author_premium": false, "can_gild": false, "link_id": "t3_1t10351", "unrepliable_reason": null, "author_flair_text_color": null, "score_hidden": false, "permalink": "/r/RoFiscalitate2/comments/1t10351/poprire_what/ok0ryp8/", "subreddit_type": "public", "locked": false, "report_reasons": null, "created": 1777969084.0, "author_flair_text": null, "treatment_tags": [], "created_utc": 1777969084.0, "subreddit_name_prefixed": "r/RoFiscalitate2", "controversiality": 0, "depth": 3, "author_flair_background_color": null, "collapsed_because_crowd_control": null, "mod_reports": [], "num_reports": null, "ups": 1}}], "before": null}}, "user_reports": [], "saved": false, "id": "ojgx0rr", "banned_at_utc": null, "mod_reason_title": null, "gilded": 0, "archived": false, "collapsed_reason_code": null, "no_follow": true, "author": "GabryelPH", "can_mod_post": false, "send_replies": true, "parent_id": "t1_ojgo1gn", "score": 3, "author_fullname": "t2_3pw5u8ng", "removal_reason": null, "approved_by": null, "mod_note": null, "all_awardings": [], "body": "Da. Este o mare prostie dar sunt sigur c\u0103 este o gre\u0219eal\u0103 pe undeva. Revin cu r\u0103spunsul ANAF.", "edited": false, "top_awarded_type": null, "downs": 0, "author_flair_css_class": null, "name": "t1_ojgx0rr", "is_submitter": true, "collapsed": false, "author_flair_richtext": [], "author_patreon_flair": false, "body_html": "&lt;div class=\"md\"&gt;&lt;p&gt;Da. Este o mare prostie dar sunt sigur c\u0103 este o gre\u0219eal\u0103 pe undeva. Revin cu r\u0103spunsul ANAF.&lt;/p&gt;\n&lt;/div&gt;", "gildings": {}, "collapsed_reason": null, "distinguished": null, "associated_award": null, "stickied": false, "author_premium": false, "can_gild": false, "link_id": "t3_1t10351", "unrepliable_reason": null, "author_flair_text_color": null, "score_hidden": false, "permalink": "/r/RoFiscalitate2/comments/1t10351/poprire_what/ojgx0rr/", "subreddit_type": "public", "locked": false, "report_reasons": null, "created": 1777709974.0, "author_flair_text": null, "treatment_tags": [], "created_utc": 1777709974.0, "subreddit_name_prefixed": "r/RoFiscalitate2", "controversiality": 0, "depth": 2, "author_flair_background_color": null, "collapsed_because_crowd_control": null, "mod_reports": [], "num_reports": null, "ups": 3}}], "before": null}}, "user_reports": [], "saved": false, "id": "ojgo1gn", "banned_at_utc": null, "mod_reason_title": null, "gilded": 0, "archived": false, "collapsed_reason_code": null, "no_follow": false, "author": "Secure-Scratch8910", "can_mod_post": false, "created_utc": 1777705160.0, "send_replies": true, "parent_id": "t1_ojgh8bm", "score": 6, "author_fullname": "t2_4txwm56u", "removal_reason": null, "approved_by": null, "mod_note": null, "all_awardings": [], "body": "Chiar sunt curios ce r\u0103spuns \u00ee\u021bi vor da la ANAF. Prin astfel de decizii, ei deja \u00eencurajeaz\u0103 prest\u0103rile de servicii la negru. S\u0103 presupunem c\u0103 te oblig\u0103 s\u0103 pl\u0103te\u0219ti de acum, de\u0219i nunta ta e abia peste c\u00e2teva luni. Ce faci dac\u0103, \u00een ziua nun\u021bii, fotograful nu mai vine pentru c\u0103 nu a primit niciun ban? Stai s\u0103 cau\u021bi altul pe ultima sut\u0103 de metri \u0219i apoi judec\u0103-te cu primul ca s\u0103-\u021bi recuperezi banii... Bani pe care nu \u0219tiu dac\u0103-i vei mai vedea vreodat\u0103, deoarece statul \u00eencaseaz\u0103 primul, iar abia apoi ajung la \u201esclavi\u201d, daca mai r\u0103m\u00e2ne ceva.", "edited": false, "top_awarded_type": null, "author_flair_css_class": null, "name": "t1_ojgo1gn", "is_submitter": false, "downs": 0, "author_flair_richtext": [], "author_patreon_flair": false, "body_html": "&lt;div class=\"md\"&gt;&lt;p&gt;Chiar sunt curios ce r\u0103spuns \u00ee\u021bi vor da la ANAF. Prin astfel de decizii, ei deja \u00eencurajeaz\u0103 prest\u0103rile de servicii la negru. S\u0103 presupunem c\u0103 te oblig\u0103 s\u0103 pl\u0103te\u0219ti de acum, de\u0219i nunta ta e abia peste c\u00e2teva luni. Ce faci dac\u0103, \u00een ziua nun\u021bii, fotograful nu mai vine pentru c\u0103 nu a primit niciun ban? Stai s\u0103 cau\u021bi altul pe ultima sut\u0103 de metri \u0219i apoi judec\u0103-te cu primul ca s\u0103-\u021bi recuperezi banii... Bani pe care nu \u0219tiu dac\u0103-i vei mai vedea vreodat\u0103, deoarece statul \u00eencaseaz\u0103 primul, iar abia apoi ajung la \u201esclavi\u201d, daca mai r\u0103m\u00e2ne ceva.&lt;/p&gt;\n&lt;/div&gt;", "gildings": {}, "collapsed_reason": null, "distinguished": null, "associated_award": null, "stickied": false, "author_premium": false, "can_gild": false, "link_id": "t3_1t10351", "unrepliable_reason": null, "author_flair_text_color": null, "score_hidden": false, "permalink": "/r/RoFiscalitate2/comments/1t10351/poprire_what/ojgo1gn/", "subreddit_type": "public", "locked": false, "report_reasons": null, "created": 1777705160.0, "author_flair_text": null, "treatment_tags": [], "collapsed": false, "subreddit_name_prefixed": "r/RoFiscalitate2", "controversiality": 0, "depth": 1, "author_flair_background_color": null, "collapsed_because_crowd_control": null, "mod_reports": [], "num_reports": null, "ups": 6}}], "before": null}}, "user_reports": [], "saved": false, "id": "ojgh8bm", "banned_at_utc": null, "mod_reason_title": null, "gilded": 0, "archived": false, "collapsed_reason_code": null, "no_follow": false, "author": "GabryelPH", "can_mod_post": false, "created_utc": 1777701682.0, "send_replies": true, "parent_id": "t3_1t10351", "score": 7, "author_fullname": "t2_3pw5u8ng", "approved_by": null, "mod_note": null, "all_awardings": [], "collapsed": false, "body": "Va mul\u021bumesc pentru r\u0103spunsuri. Are sens ce spune\u021bi, de\u0219i mi se pare de o absolut\u0103 imbecilitate. Unu la m\u00e2na, ce treab\u0103 avem noi PF cu datoriile firmelor de la care cump\u0103r\u0103m servicii; ajungem sa \u00eentreb\u0103m \u00eenainte de semnare contract sau emitere factura daca au impozitele pl\u0103tite? Doi la m\u00e2n\u0103, ce treab\u0103 as avea eu sa pl\u0103tesc (ipotetic vorbind) niste taxe/impozite pentru un serviciu care \u00een acest moment nu a fost prestat, mai sunt luni p\u00e2n\u0103 se va \u00eent\u00e2mpla acel serviciu. \n\nMerg luni la ANAF \u0219i sper sa rezolv direct acolo. O sa las r\u0103spuns aici, poate va ajuta in viitor pe cineva. Mul\u021bumesc din nou!", "edited": false, "top_awarded_type": null, "author_flair_css_class": null, "name": "t1_ojgh8bm", "is_submitter": true, "downs": 0, "author_flair_richtext": [], "author_patreon_flair": false, "body_html": "&lt;div class=\"md\"&gt;&lt;p&gt;Va mul\u021bumesc pentru r\u0103spunsuri. Are sens ce spune\u021bi, de\u0219i mi se pare de o absolut\u0103 imbecilitate. Unu la m\u00e2na, ce treab\u0103 avem noi PF cu datoriile firmelor de la care cump\u0103r\u0103m servicii; ajungem sa \u00eentreb\u0103m \u00eenainte de semnare contract sau emitere factura daca au impozitele pl\u0103tite? Doi la m\u00e2n\u0103, ce treab\u0103 as avea eu sa pl\u0103tesc (ipotetic vorbind) niste taxe/impozite pentru un serviciu care \u00een acest moment nu a fost prestat, mai sunt luni p\u00e2n\u0103 se va \u00eent\u00e2mpla acel serviciu. &lt;/p&gt;\n\n&lt;p&gt;Merg luni la ANAF \u0219i sper sa rezolv direct acolo. O sa las r\u0103spuns aici, poate va ajuta in viitor pe cineva. Mul\u021bumesc din nou!&lt;/p&gt;\n&lt;/div&gt;", "removal_reason": null, "collapsed_reason": null, "distinguished": null, "associated_award": null, "stickied": false, "author_premium": false, "can_gild": false, "gildings": {}, "unrepliable_reason": null, "author_flair_text_color": null, "score_hidden": false, "permalink": "/r/RoFiscalitate2/comments/1t10351/poprire_what/ojgh8bm/", "subreddit_type": "public", "locked": false, "report_reasons": null, "created": 1777701682.0, "author_flair_text": null, "treatment_tags": [], "link_id": "t3_1t10351", "subreddit_name_prefixed": "r/RoFiscalitate2", "controversiality": 0, "depth": 0, "author_flair_background_color": null, "collapsed_because_crowd_control": null, "mod_reports": [], "num_reports": null, "ups": 7}}, {"kind": "t1", "data": {"subreddit_id": "t5_ap8imo", "approved_at_utc": null, "author_is_blocked": false, "comment_type": null, "awarders": [], "mod_reason_by": null, "banned_by": null, "author_flair_type": "text", "total_awards_received": 0, "subreddit": "RoFiscalitate2", "author_flair_template_id": null, "likes": null, "replies": {"kind": "Listing", "data": {"after": null, "dist": null, "modhash": "", "geo_filter": "", "children": [{"kind": "t1", "data": {"subreddit_id": "t5_ap8imo", "approved_at_utc": null, "author_is_blocked": false, "comment_type": null, "awarders": [], "mod_reason_by": null, "banned_by": null, "author_flair_type": "text", "total_awards_received": 0, "subreddit": "RoFiscalitate2", "author_flair_template_id": null, "likes": null, "replies": {"kind": "Listing", "data": {"after": null, "dist": null, "modhash": "", "geo_filter": "", "children": [{"kind": "t1", "data": {"subreddit_id": "t5_ap8imo", "approved_at_utc": null, "author_is_blocked": false, "comment_type": null, "awarders": [], "mod_reason_by": null, "banned_by": null, "author_flair_type": "text", "total_awards_received": 0, "subreddit": "RoFiscalitate2", "author_flair_template_id": null, "likes": null, "replies": {"kind": "Listing", "data": {"after": null, "dist": null, "modhash": "", "geo_filter": "", "children": [{"kind": "t1", "data": {"subreddit_id": "t5_ap8imo", "approved_at_utc": null, "author_is_blocked": false, "comment_type": null, "awarders": [], "mod_reason_by": null, "banned_by": null, "author_flair_type": "text", "total_awards_received": 0, "subreddit": "RoFiscalitate2", "author_flair_template_id": null, "likes": null, "replies": {"kind": "Listing", "data": {"after": null, "dist": null, "modhash": "", "geo_filter": "", "children": [{"kind": "t1", "data": {"subreddit_id": "t5_ap8imo", "approved_at_utc": null, "author_is_blocked": false, "comment_type": null, "awarders": [], "mod_reason_by": null, "banned_by": null, "author_flair_type": "text", "total_awards_received": 0, "subreddit": "RoFiscalitate2", "author_flair_template_id": null, "distinguished": null, "likes": null, "replies": "", "user_reports": [], "saved": false, "id": "ojdbzaa", "banned_at_utc": null, "mod_reason_title": null, "gilded": 0, "archived": false, "collapsed_reason_code": null, "no_follow": false, "author": "manu144x", "can_mod_post": false, "send_replies": true, "parent_id": "t1_ojd9oq4", "score": 3, "author_fullname": "t2_eec62uo", "removal_reason": null, "approved_by": null, "mod_note": null, "all_awardings": [], "body": "Repet, treaba e invers.\n\nEi execut\u0103 procedura, \u0219i TU trebuie s\u0103 dovede\u0219ti c\u0103 nu s-au prestat serviciile sau c\u0103 nu s-a f\u0103cut nu \u0219tiu ce.\n\nA \u0219i scris OP \u00een postare, ultimul paragraf:\n\n&gt;\u00cen situa\u0163ia \u00een care, la data comunic\u0103rii prezentei adrese **nu datora\u0163i** vreo sum\u0103 de bani debitorului (Firma X) cu domiciliul fiscal in (...) sau **nu ve\u0163i datora** \u00een viitor asemenea sume \u00een temeiul unor raporturijuridice existente, **ve\u0163i \u00een\u015ftiin\u0163a despre acest fapt organul de executare** silit\u0103 \u00een termen de 5 zile de la primirea prezentei adrese.", "edited": false, "author_flair_css_class": null, "name": "t1_ojdbzaa", "is_submitter": false, "downs": 0, "author_flair_richtext": [], "author_patreon_flair": false, "body_html": "&lt;div class=\"md\"&gt;&lt;p&gt;Repet, treaba e invers.&lt;/p&gt;\n\n&lt;p&gt;Ei execut\u0103 procedura, \u0219i TU trebuie s\u0103 dovede\u0219ti c\u0103 nu s-au prestat serviciile sau c\u0103 nu s-a f\u0103cut nu \u0219tiu ce.&lt;/p&gt;\n\n&lt;p&gt;A \u0219i scris OP \u00een postare, ultimul paragraf:&lt;/p&gt;\n\n&lt;blockquote&gt;\n&lt;p&gt;\u00cen situa\u0163ia \u00een care, la data comunic\u0103rii prezentei adrese &lt;strong&gt;nu datora\u0163i&lt;/strong&gt; vreo sum\u0103 de bani debitorului (Firma X) cu domiciliul fiscal in (...) sau &lt;strong&gt;nu ve\u0163i datora&lt;/strong&gt; \u00een viitor asemenea sume \u00een temeiul unor raporturijuridice existente, &lt;strong&gt;ve\u0163i \u00een\u015ftiin\u0163a despre acest fapt organul de executare&lt;/strong&gt; silit\u0103 \u00een termen de 5 zile de la primirea prezentei adrese.&lt;/p&gt;\n&lt;/blockquote&gt;\n&lt;/div&gt;", "gildings": {}, "collapsed_reason": null, "link_id": "t3_1t10351", "associated_award": null, "stickied": false, "author_premium": false, "can_gild": false, "top_awarded_type": null, "unrepliable_reason": null, "author_flair_text_color": null, "treatment_tags": [], "score_hidden": false, "permalink": "/r/RoFiscalitate2/comments/1t10351/poprire_what/ojdbzaa/", "subreddit_type": "public", "locked": false, "report_reasons": null, "created": 1777661584.0, "author_flair_text": null, "collapsed": false, "created_utc": 1777661584.0, "subreddit_name_prefixed": "r/RoFiscalitate2", "controversiality": 0, "depth": 4, "author_flair_background_color": null, "collapsed_because_crowd_control": null, "mod_reports": [], "num_reports": null, "ups": 3}}], "before": null}}, "user_reports": [], "saved": false, "id": "ojd9oq4", "banned_at_utc": null, "mod_reason_title": null, "gilded": 0, "archived": false, "collapsed_reason_code": null, "no_follow": false, "author": "Miserable-Bug-2255", "can_mod_post": false, "send_replies": true, "parent_id": "t1_ojd6xdx", "score": 5, "author_fullname": "t2_13k55diw5p", "removal_reason": null, "approved_by": null, "mod_note": null, "all_awardings": [], "collapsed": false, "body": "Pai sumele dup\u0103 contract sunt pentru prestarea unor servicii. Daca ANAF cere banii, se face si ANAF fotograf la nunta?", "edited": false, "top_awarded_type": null, "author_flair_css_class": null, "name": "t1_ojd9oq4", "is_submitter": false, "downs": 0, "author_flair_richtext": [], "author_patreon_flair": false, "body_html": "&lt;div class=\"md\"&gt;&lt;p&gt;Pai sumele dup\u0103 contract sunt pentru prestarea unor servicii. Daca ANAF cere banii, se face si ANAF fotograf la nunta?&lt;/p&gt;\n&lt;/div&gt;", "gildings": {}, "collapsed_reason": null, "distinguished": null, "associated_award": null, "stickied": false, "author_premium": false, "can_gild": false, "link_id": "t3_1t10351", "unrepliable_reason": null, "author_flair_text_color": null, "score_hidden": false, "permalink": "/r/RoFiscalitate2/comments/1t10351/poprire_what/ojd9oq4/", "subreddit_type": "public", "locked": false, "report_reasons": null, "created": 1777660934.0, "author_flair_text": null, "treatment_tags": [], "created_utc": 1777660934.0, "subreddit_name_prefixed": "r/RoFiscalitate2", "controversiality": 0, "depth": 3, "author_flair_background_color": null, "collapsed_because_crowd_control": null, "mod_reports": [], "num_reports": null, "ups": 5}}], "before": null}}, "user_reports": [], "saved": false, "id": "ojd6xdx", "banned_at_utc": null, "mod_reason_title": null, "gilded": 0, "archived": false, "collapsed_reason_code": null, "no_follow": false, "author": "manu144x", "can_mod_post": false, "send_replies": true, "parent_id": "t1_ojd14js", "score": 10, "author_fullname": "t2_eec62uo", "removal_reason": null, "approved_by": null, "mod_note": null, "all_awardings": [], "body": "Nu neaparat.\n\nANAF se face st\u0103p\u00e2n pe acele datorii, deci dac\u0103 tu ai semnat cu ei un contract \u0219i va trebui s\u0103 le pl\u0103te\u0219ti o sum\u0103, ANAF \u00ee\u021bi poate popri \u021bie contul s\u0103 ia suma de la tine, pentru c\u0103 se consider\u0103 datorie executorie.\n\nDa, e ridicol, dar e perfect posibil. De asta \u0219i aici scrie, c\u0103 merge de la sine, \u0219i dac\u0103 tu NU datorezi bani, TU e\u0219ti cel care trebuie s\u0103 ceri desfiin\u021barea popririi.\n\nDeci din oficiu, se \u00eenfiin\u021beaz\u0103 poprirea, omul are dreptate.", "edited": false, "top_awarded_type": null, "downs": 0, "author_flair_css_class": null, "name": "t1_ojd6xdx", "is_submitter": false, "collapsed": false, "author_flair_richtext": [], "author_patreon_flair": false, "body_html": "&lt;div class=\"md\"&gt;&lt;p&gt;Nu neaparat.&lt;/p&gt;\n\n&lt;p&gt;ANAF se face st\u0103p\u00e2n pe acele datorii, deci dac\u0103 tu ai semnat cu ei un contract \u0219i va trebui s\u0103 le pl\u0103te\u0219ti o sum\u0103, ANAF \u00ee\u021bi poate popri \u021bie contul s\u0103 ia suma de la tine, pentru c\u0103 se consider\u0103 datorie executorie.&lt;/p&gt;\n\n&lt;p&gt;Da, e ridicol, dar e perfect posibil. De asta \u0219i aici scrie, c\u0103 merge de la sine, \u0219i dac\u0103 tu NU datorezi bani, TU e\u0219ti cel care trebuie s\u0103 ceri desfiin\u021barea popririi.&lt;/p&gt;\n\n&lt;p&gt;Deci din oficiu, se \u00eenfiin\u021beaz\u0103 poprirea, omul are dreptate.&lt;/p&gt;\n&lt;/div&gt;", "gildings": {}, "collapsed_reason": null, "distinguished": null, "associated_award": null, "stickied": false, "author_premium": false, "can_gild": false, "link_id": "t3_1t10351", "unrepliable_reason": null, "author_flair_text_color": null, "score_hidden": false, "permalink": "/r/RoFiscalitate2/comments/1t10351/poprire_what/ojd6xdx/", "subreddit_type": "public", "locked": false, "report_reasons": null, "created": 1777660140.0, "author_flair_text": null, "treatment_tags": [], "created_utc": 1777660140.0, "subreddit_name_prefixed": "r/RoFiscalitate2", "controversiality": 0, "depth": 2, "author_flair_background_color": null, "collapsed_because_crowd_control": null, "mod_reports": [], "num_reports": null, "ups": 10}}], "before": null}}, "user_reports": [], "saved": false, "id": "ojd14js", "banned_at_utc": null, "mod_reason_title": null, "gilded": 0, "archived": false, "collapsed_reason_code": null, "no_follow": false, "author": "andrei_samiir", "can_mod_post": false, "created_utc": 1777658503.0, "send_replies": true, "parent_id": "t1_ojczawc", "score": 15, "author_fullname": "t2_gp4a7", "removal_reason": null, "approved_by": null, "mod_note": null, "all_awardings": [], "body": "Firma X are datorii la stat. ANAF te a instiintat ca nu mai ai voie sa platesti nimic firmei X. Orice bani mai ai de dat firmei X trebuie sa ii dai ANAFului. Atat.", "edited": false, "top_awarded_type": null, "author_flair_css_class": null, "name": "t1_ojd14js", "is_submitter": false, "downs": 0, "author_flair_richtext": [], "author_patreon_flair": false, "body_html": "&lt;div class=\"md\"&gt;&lt;p&gt;Firma X are datorii la stat. ANAF te a instiintat ca nu mai ai voie sa platesti nimic firmei X. Orice bani mai ai de dat firmei X trebuie sa ii dai ANAFului. Atat.&lt;/p&gt;\n&lt;/div&gt;", "gildings": {}, "collapsed_reason": null, "distinguished": null, "associated_award": null, "stickied": false, "author_premium": false, "can_gild": false, "link_id": "t3_1t10351", "unrepliable_reason": null, "author_flair_text_color": null, "score_hidden": false, "permalink": "/r/RoFiscalitate2/comments/1t10351/poprire_what/ojd14js/", "subreddit_type": "public", "locked": false, "report_reasons": null, "created": 1777658503.0, "author_flair_text": null, "treatment_tags": [], "collapsed": false, "subreddit_name_prefixed": "r/RoFiscalitate2", "controversiality": 0, "depth": 1, "author_flair_background_color": null, "collapsed_because_crowd_control": null, "mod_reports": [], "num_reports": null, "ups": 15}}, {"kind": "t1", "data": {"subreddit_id": "t5_ap8imo", "approved_at_utc": null, "author_is_blocked": false, "comment_type": null, "awarders": [], "mod_reason_by": null, "banned_by": null, "author_flair_type": "text", "total_awards_received": 0, "subreddit": "RoFiscalitate2", "author_flair_template_id": null, "likes": null, "replies": "", "user_reports": [], "saved": false, "id": "ojdyikk", "banned_at_utc": null, "mod_reason_title": null, "gilded": 0, "archived": false, "collapsed_reason_code": null, "no_follow": false, "author": "meclaus", "can_mod_post": false, "created_utc": 1777668091.0, "send_replies": true, "parent_id": "t1_ojczawc", "score": 8, "author_fullname": "t2_2hgepso4", "removal_reason": null, "approved_by": null, "mod_note": null, "all_awardings": [], "body": "Esti tert poprit, nu ai tu poprire pe conturile tale, daca ai datorii la respectivul va trebui sa le platesti anaf.ului. Daca ai datorii si nu le platesti la scadenta anaf.ul poatr face o actiune in instanta numita validare poprire ( sau o actiune oblica) si abia atunci daca instanta admite actiunea definitiv acea sentinta va fi titlu executoriu impotriva ta pt sumele datorate de catre tine lui x.", "edited": false, "top_awarded_type": null, "author_flair_css_class": null, "name": "t1_ojdyikk", "is_submitter": false, "downs": 0, "author_flair_richtext": [], "author_patreon_flair": false, "body_html": "&lt;div class=\"md\"&gt;&lt;p&gt;Esti tert poprit, nu ai tu poprire pe conturile tale, daca ai datorii la respectivul va trebui sa le platesti anaf.ului. Daca ai datorii si nu le platesti la scadenta anaf.ul poatr face o actiune in instanta numita validare poprire ( sau o actiune oblica) si abia atunci daca instanta admite actiunea definitiv acea sentinta va fi titlu executoriu impotriva ta pt sumele datorate de catre tine lui x.&lt;/p&gt;\n&lt;/div&gt;", "gildings": {}, "collapsed_reason": null, "distinguished": null, "associated_award": null, "stickied": false, "author_premium": false, "can_gild": false, "link_id": "t3_1t10351", "unrepliable_reason": null, "author_flair_text_color": null, "score_hidden": false, "permalink": "/r/RoFiscalitate2/comments/1t10351/poprire_what/ojdyikk/", "subreddit_type": "public", "locked": false, "report_reasons": null, "created": 1777668091.0, "author_flair_text": null, "treatment_tags": [], "collapsed": false, "subreddit_name_prefixed": "r/RoFiscalitate2", "controversiality": 0, "depth": 1, "author_flair_background_color": null, "collapsed_because_crowd_control": null, "mod_reports": [], "num_reports": null, "ups": 8}}], "before": null}}, "user_reports": [], "saved": false, "id": "ojczawc", "banned_at_utc": null, "mod_reason_title": null, "gilded": 0, "archived": false, "collapsed_reason_code": null, "no_follow": false, "author": "GabryelPH", "can_mod_post": false, "created_utc": 1777658004.0, "send_replies": true, "parent_id": "t3_1t10351", "score": 7, "author_fullname": "t2_3pw5u8ng", "approved_by": null, "mod_note": null, "all_awardings": [], "collapsed": false, "body": "Mul\u021bumesc pentru r\u0103spunsuri. Asta este in ambele documente de la ANAF:\n\n\u00cen temeiul prevederilor art. 236 alin. (5) din Legea nr. 207/2015 privind Codul de procedur\u0103 fiscal\u0103, cu modific\u0103rile \u015fi complet\u0103rile ulterioare, se \u00eenfiin\u0163eaz\u0103 poprirea asupra sumelor de bani reprezent\u00e2nd venituri \u015fi disponibilit\u0103\u0163i b\u0103ne\u015fti \u00een lei \u015fi \u00een valut\u0103, titluri de valoare sau alte bunuri mobile necorporale, de\u0163inute \u015fi/saudatorate, cu orice titlu, debitorului X cu domiciliul fiscal in judetul (...) de c\u0103tre dumneavoastr\u0103 sau pe care le ve\u0163i datora \u015fi/sau de\u0163ine \u00een viitor \u00een temeiul unor raporturi juridice existente. Sumele urm\u0103ribile vor fi re\u0163inute \u015fi virate, de \u00eendat\u0103, \u00een conturile deschise la unitatea de Trezorerie a Statului Trezorerie (..), pe numele (Firma X), utiliz\u00e2nd num\u0103rul de eviden\u0163\u0103 a pl\u0103\u0163ii 12345, dup\u0103 cum urmeaz\u0103: un tabel cu sume reprezent\u00e2nd impozite \u0219i contribu\u021bii.\n\nPoprirea se consider\u0103 \u00eenfiin\u0163at\u0103 din momentul primirii adresei de \u00eenfiin\u0163are de c\u0103tre dumneavoastr\u0103. \u00cen acest sens, ave\u0163i obliga\u0163ia s\u0103 \u00eenregistra\u0163i at\u00e2t ziua, c\u00e2t \u015fi ora primirii adresei de \u00eenfiin\u0163are a popririi.\n\n\u00cen situa\u0163ia \u00een care, la data comunic\u0103rii prezentei adrese nu datora\u0163i vreo sum\u0103 de bani debitorului (Firma X) cu domiciliul fiscal in (...) sau nu ve\u0163i datora \u00een viitor asemenea sume \u00een temeiul unor raporturijuridice existente, ve\u0163i \u00een\u015ftiin\u0163a despre acest fapt organul de executare silit\u0103 \u00een termen de 5 zile de la primirea prezentei adrese.", "edited": false, "top_awarded_type": null, "author_flair_css_class": null, "name": "t1_ojczawc", "is_submitter": true, "downs": 0, "author_flair_richtext": [], "author_patreon_flair": false, "body_html": "&lt;div class=\"md\"&gt;&lt;p&gt;Mul\u021bumesc pentru r\u0103spunsuri. Asta este in ambele documente de la ANAF:&lt;/p&gt;\n\n&lt;p&gt;\u00cen temeiul prevederilor art. 236 alin. (5) din Legea nr. 207/2015 privind Codul de procedur\u0103 fiscal\u0103, cu modific\u0103rile \u015fi complet\u0103rile ulterioare, se \u00eenfiin\u0163eaz\u0103 poprirea asupra sumelor de bani reprezent\u00e2nd venituri \u015fi disponibilit\u0103\u0163i b\u0103ne\u015fti \u00een lei \u015fi \u00een valut\u0103, titluri de valoare sau alte bunuri mobile necorporale, de\u0163inute \u015fi/saudatorate, cu orice titlu, debitorului X cu domiciliul fiscal in judetul (...) de c\u0103tre dumneavoastr\u0103 sau pe care le ve\u0163i datora \u015fi/sau de\u0163ine \u00een viitor \u00een temeiul unor raporturi juridice existente. Sumele urm\u0103ribile vor fi re\u0163inute \u015fi virate, de \u00eendat\u0103, \u00een conturile deschise la unitatea de Trezorerie a Statului Trezorerie (..), pe numele (Firma X), utiliz\u00e2nd num\u0103rul de eviden\u0163\u0103 a pl\u0103\u0163ii 12345, dup\u0103 cum urmeaz\u0103: un tabel cu sume reprezent\u00e2nd impozite \u0219i contribu\u021bii.&lt;/p&gt;\n\n&lt;p&gt;Poprirea se consider\u0103 \u00eenfiin\u0163at\u0103 din momentul primirii adresei de \u00eenfiin\u0163are de c\u0103tre dumneavoastr\u0103. \u00cen acest sens, ave\u0163i obliga\u0163ia s\u0103 \u00eenregistra\u0163i at\u00e2t ziua, c\u00e2t \u015fi ora primirii adresei de \u00eenfiin\u0163are a popririi.&lt;/p&gt;\n\n&lt;p&gt;\u00cen situa\u0163ia \u00een care, la data comunic\u0103rii prezentei adrese nu datora\u0163i vreo sum\u0103 de bani debitorului (Firma X) cu domiciliul fiscal in (...) sau nu ve\u0163i datora \u00een viitor asemenea sume \u00een temeiul unor raporturijuridice existente, ve\u0163i \u00een\u015ftiin\u0163a despre acest fapt organul de executare silit\u0103 \u00een termen de 5 zile de la primirea prezentei adrese.&lt;/p&gt;\n&lt;/div&gt;", "removal_reason": null, "collapsed_reason": null, "distinguished": null, "associated_award": null, "stickied": false, "author_premium": false, "can_gild": false, "gildings": {}, "unrepliable_reason": null, "author_flair_text_color": null, "score_hidden": false, "permalink": "/r/RoFiscalitate2/comments/1t10351/poprire_what/ojczawc/", "subreddit_type": "public", "locked": false, "report_reasons": null, "created": 1777658004.0, "author_flair_text": null, "treatment_tags": [], "link_id": "t3_1t10351", "subreddit_name_prefixed": "r/RoFiscalitate2", "controversiality": 0, "depth": 0, "author_flair_background_color": null, "collapsed_because_crowd_control": null, "mod_reports": [], "num_reports": null, "ups": 7}}, {"kind": "t1", "data": {"subreddit_id": "t5_ap8imo", "approved_at_utc": null, "author_is_blocked": false, "comment_type": null, "awarders": [], "mod_reason_by": null, "banned_by": null, "author_flair_type": "text", "total_awards_received": 0, "subreddit": "RoFiscalitate2", "author_flair_template_id": null, "likes": null, "replies": {"kind": "Listing", "data": {"after": null, "dist": null, "modhash": "", "geo_filter": "", "children": [{"kind": "t1", "data": {"subreddit_id": "t5_ap8imo", "approved_at_utc": null, "author_is_blocked": false, "comment_type": null, "awarders": [], "mod_reason_by": null, "banned_by": null, "author_flair_type": "text", "total_awards_received": 0, "subreddit": "RoFiscalitate2", "author_flair_template_id": null, "likes": null, "replies": {"kind": "Listing", "data": {"after": null, "dist": null, "modhash": "", "geo_filter": "", "children": [{"kind": "t1", "data": {"subreddit_id": "t5_ap8imo", "approved_at_utc": null, "author_is_blocked": false, "comment_type": null, "awarders": [], "mod_reason_by": null, "banned_by": null, "author_flair_type": "text", "total_awards_received": 0, "subreddit": "RoFiscalitate2", "author_flair_template_id": null, "likes": null, "replies": {"kind": "Listing", "data": {"after": null, "dist": null, "modhash": "", "geo_filter": "", "children": [{"kind": "t1", "data": {"subreddit_id": "t5_ap8imo", "approved_at_utc": null, "author_is_blocked": false, "comment_type": null, "awarders": [], "mod_reason_by": null, "banned_by": null, "author_flair_type": "text", "total_awards_received": 0, "subreddit": "RoFiscalitate2", "author_flair_template_id": null, "likes": null, "replies": "", "user_reports": [], "saved": false, "id": "ojo1bjt", "banned_at_utc": null, "mod_reason_title": null, "gilded": 0, "archived": false, "collapsed_reason_code": null, "no_follow": true, "author": "harubax", "can_mod_post": false, "send_replies": true, "parent_id": "t1_ojnzw9v", "score": 2, "author_fullname": "t2_12z3rh", "removal_reason": null, "approved_by": null, "mod_note": null, "all_awardings": [], "collapsed": false, "body": "OP mai are de achitat 8000 de lei, c\u00e2t prevede contractul \u0219i abia dup\u0103 ce firma presteaz\u0103 serviciile.\n\nEste destul de clar ce scrie acolo, problema e c\u0103 firma r\u0103m\u00e2ne \u00een ofsaid dac\u0103 a\u0219teapt\u0103 \u00eencas\u0103ri semnificative \u0219i toate se duc direct \u00een Trezorerie. Poprirea se instituie \u0219i la b\u0103nci pe suma respectiv\u0103. Nu \u0219tiu c\u00e2t dureaz\u0103 s\u0103 primeasc\u0103 banii de la stat.", "edited": false, "top_awarded_type": null, "author_flair_css_class": null, "name": "t1_ojo1bjt", "is_submitter": false, "downs": 0, "author_flair_richtext": [], "author_patreon_flair": false, "body_html": "&lt;div class=\"md\"&gt;&lt;p&gt;OP mai are de achitat 8000 de lei, c\u00e2t prevede contractul \u0219i abia dup\u0103 ce firma presteaz\u0103 serviciile.&lt;/p&gt;\n\n&lt;p&gt;Este destul de clar ce scrie acolo, problema e c\u0103 firma r\u0103m\u00e2ne \u00een ofsaid dac\u0103 a\u0219teapt\u0103 \u00eencas\u0103ri semnificative \u0219i toate se duc direct \u00een Trezorerie. Poprirea se instituie \u0219i la b\u0103nci pe suma respectiv\u0103. Nu \u0219tiu c\u00e2t dureaz\u0103 s\u0103 primeasc\u0103 banii de la stat.&lt;/p&gt;\n&lt;/div&gt;", "gildings": {}, "collapsed_reason": null, "distinguished": null, "associated_award": null, "stickied": false, "author_premium": false, "can_gild": false, "link_id": "t3_1t10351", "unrepliable_reason": null, "author_flair_text_color": null, "score_hidden": false, "permalink": "/r/RoFiscalitate2/comments/1t10351/poprire_what/ojo1bjt/", "subreddit_type": "public", "locked": false, "report_reasons": null, "created": 1777809528.0, "author_flair_text": null, "treatment_tags": [], "created_utc": 1777809528.0, "subreddit_name_prefixed": "r/RoFiscalitate2", "controversiality": 0, "depth": 3, "author_flair_background_color": null, "collapsed_because_crowd_control": null, "mod_reports": [], "num_reports": null, "ups": 2}}], "before": null}}, "user_reports": [], "saved": false, "id": "ojnzw9v", "banned_at_utc": null, "mod_reason_title": null, "gilded": 0, "archived": false, "collapsed_reason_code": null, "no_follow": true, "author": "Glass-Fun408", "can_mod_post": false, "send_replies": true, "parent_id": "t1_ojn0dft", "score": 2, "author_fullname": "t2_15ya5phu8c", "removal_reason": null, "approved_by": null, "mod_note": null, "all_awardings": [], "body": "OP spune c\u0103 a achitat o factur\u0103 de avans de 2.000 lei. Poprirea este de 23K lei pentru care nici nu \u0219tie dac\u0103 s-au emis facturi. Firma poate s\u0103 spun\u0103 c\u0103 are de \u00eencasat de la el orice sum\u0103 de bani f\u0103r\u0103 fi verificat\u0103. Tot OP trebuie s\u0103 mearg\u0103 s\u0103 clarifice.", "edited": false, "top_awarded_type": null, "downs": 0, "author_flair_css_class": null, "name": "t1_ojnzw9v", "is_submitter": false, "collapsed": false, "author_flair_richtext": [], "author_patreon_flair": false, "body_html": "&lt;div class=\"md\"&gt;&lt;p&gt;OP spune c\u0103 a achitat o factur\u0103 de avans de 2.000 lei. Poprirea este de 23K lei pentru care nici nu \u0219tie dac\u0103 s-au emis facturi. Firma poate s\u0103 spun\u0103 c\u0103 are de \u00eencasat de la el orice sum\u0103 de bani f\u0103r\u0103 fi verificat\u0103. Tot OP trebuie s\u0103 mearg\u0103 s\u0103 clarifice.&lt;/p&gt;\n&lt;/div&gt;", "gildings": {}, "collapsed_reason": null, "distinguished": null, "associated_award": null, "stickied": false, "author_premium": false, "can_gild": false, "link_id": "t3_1t10351", "unrepliable_reason": null, "author_flair_text_color": null, "score_hidden": false, "permalink": "/r/RoFiscalitate2/comments/1t10351/poprire_what/ojnzw9v/", "subreddit_type": "public", "locked": false, "report_reasons": null, "created": 1777808937.0, "author_flair_text": null, "treatment_tags": [], "created_utc": 1777808937.0, "subreddit_name_prefixed": "r/RoFiscalitate2", "controversiality": 0, "depth": 2, "author_flair_background_color": null, "collapsed_because_crowd_control": null, "mod_reports": [], "num_reports": null, "ups": 2}}], "before": null}}, "user_reports": [], "saved": false, "id": "ojn0dft", "banned_at_utc": null, "mod_reason_title": null, "gilded": 0, "archived": false, "collapsed_reason_code": null, "no_follow": true, "author": "harubax", "can_mod_post": false, "created_utc": 1777790585.0, "send_replies": true, "parent_id": "t1_ojcwzu0", "score": 3, "author_fullname": "t2_12z3rh", "removal_reason": null, "approved_by": null, "mod_note": null, "all_awardings": [], "body": "Datoriile sunt reale, dar nu sunt ale tale ci ale firmei cu care ai o rela\u021bie contractual\u0103.", "edited": false, "top_awarded_type": null, "author_flair_css_class": null, "name": "t1_ojn0dft", "is_submitter": false, "downs": 0, "author_flair_richtext": [], "author_patreon_flair": false, "body_html": "&lt;div class=\"md\"&gt;&lt;p&gt;Datoriile sunt reale, dar nu sunt ale tale ci ale firmei cu care ai o rela\u021bie contractual\u0103.&lt;/p&gt;\n&lt;/div&gt;", "gildings": {}, "collapsed_reason": null, "distinguished": null, "associated_award": null, "stickied": false, "author_premium": false, "can_gild": false, "link_id": "t3_1t10351", "unrepliable_reason": null, "author_flair_text_color": null, "score_hidden": false, "permalink": "/r/RoFiscalitate2/comments/1t10351/poprire_what/ojn0dft/", "subreddit_type": "public", "locked": false, "report_reasons": null, "created": 1777790585.0, "author_flair_text": null, "treatment_tags": [], "collapsed": false, "subreddit_name_prefixed": "r/RoFiscalitate2", "controversiality": 0, "depth": 1, "author_flair_background_color": null, "collapsed_because_crowd_control": null, "mod_reports": [], "num_reports": null, "ups": 3}}, {"kind": "t1", "data": {"subreddit_id": "t5_ap8imo", "approved_at_utc": null, "author_is_blocked": false, "comment_type": null, "awarders": [], "mod_reason_by": null, "banned_by": null, "author_flair_type": "text", "total_awards_received": 0, "subreddit": "RoFiscalitate2", "author_flair_template_id": null, "likes": null, "replies": "", "user_reports": [], "saved": false, "id": "ojcx9m5", "banned_at_utc": null, "mod_reason_title": null, "gilded": 0, "archived": false, "collapsed_reason_code": null, "no_follow": false, "author": "Routine_Bake5794", "can_mod_post": false, "created_utc": 1777657458.0, "send_replies": true, "parent_id": "t1_ojcwzu0", "score": 5, "author_fullname": "t2_8gmx1oyp", "removal_reason": null, "approved_by": null, "mod_note": null, "all_awardings": [], "body": "DA!", "edited": false, "top_awarded_type": null, "author_flair_css_class": null, "name": "t1_ojcx9m5", "is_submitter": false, "downs": 0, "author_flair_richtext": [], "author_patreon_flair": false, "body_html": "&lt;div class=\"md\"&gt;&lt;p&gt;DA!&lt;/p&gt;\n&lt;/div&gt;", "gildings": {}, "collapsed_reason": null, "distinguished": null, "associated_award": null, "stickied": false, "author_premium": false, "can_gild": false, "link_id": "t3_1t10351", "unrepliable_reason": null, "author_flair_text_color": null, "score_hidden": false, "permalink": "/r/RoFiscalitate2/comments/1t10351/poprire_what/ojcx9m5/", "subreddit_type": "public", "locked": false, "report_reasons": null, "created": 1777657458.0, "author_flair_text": null, "treatment_tags": [], "collapsed": false, "subreddit_name_prefixed": "r/RoFiscalitate2", "controversiality": 0, "depth": 1, "author_flair_background_color": null, "collapsed_because_crowd_control": null, "mod_reports": [], "num_reports": null, "ups": 5}}], "before": null}}, "user_reports": [], "saved": false, "id": "ojcwzu0", "banned_at_utc": null, "mod_reason_title": null, "gilded": 0, "archived": false, "collapsed_reason_code": null, "no_follow": false, "author": "Glass-Fun408", "can_mod_post": false, "created_utc": 1777657385.0, "send_replies": true, "parent_id": "t3_1t10351", "score": 11, "author_fullname": "t2_15ya5phu8c", "approved_by": null, "mod_note": null, "all_awardings": [], "collapsed": false, "body": "ANAF a luat-o razna? Adic\u0103 pun poprire la persoane fizice pe conturile de la banc\u0103 pentru ni\u0219te datorii care nici nu sunt reale? ", "edited": false, "top_awarded_type": null, "author_flair_css_class": null, "name": "t1_ojcwzu0", "is_submitter": false, "downs": 0, "author_flair_richtext": [], "author_patreon_flair": false, "body_html": "&lt;div class=\"md\"&gt;&lt;p&gt;ANAF a luat-o razna? Adic\u0103 pun poprire la persoane fizice pe conturile de la banc\u0103 pentru ni\u0219te datorii care nici nu sunt reale? &lt;/p&gt;\n&lt;/div&gt;", "removal_reason": null, "collapsed_reason": null, "distinguished": null, "associated_award": null, "stickied": false, "author_premium": false, "can_gild": false, "gildings": {}, "unrepliable_reason": null, "author_flair_text_color": null, "score_hidden": false, "permalink": "/r/RoFiscalitate2/comments/1t10351/poprire_what/ojcwzu0/", "subreddit_type": "public", "locked": false, "report_reasons": null, "created": 1777657385.0, "author_flair_text": null, "treatment_tags": [], "link_id": "t3_1t10351", "subreddit_name_prefixed": "r/RoFiscalitate2", "controversiality": 0, "depth": 0, "author_flair_background_color": null, "collapsed_because_crowd_control": null, "mod_reports": [], "num_reports": null, "ups": 11}}, {"kind": "t1", "data": {"subreddit_id": "t5_ap8imo", "approved_at_utc": null, "author_is_blocked": false, "comment_type": null, "awarders": [], "mod_reason_by": null, "banned_by": null, "author_flair_type": "text", "total_awards_received": 0, "subreddit": "RoFiscalitate2", "author_flair_template_id": null, "likes": null, "replies": {"kind": "Listing", "data": {"after": null, "dist": null, "modhash": "", "geo_filter": "", "children": [{"kind": "t1", "data": {"subreddit_id": "t5_ap8imo", "approved_at_utc": null, "author_is_blocked": false, "comment_type": null, "awarders": [], "mod_reason_by": null, "banned_by": null, "author_flair_type": "text", "total_awards_received": 0, "subreddit": "RoFiscalitate2", "author_flair_template_id": null, "likes": null, "replies": "", "user_reports": [], "saved": false, "id": "ojhl8ba", "banned_at_utc": null, "mod_reason_title": null, "gilded": 0, "archived": false, "collapsed_reason_code": null, "no_follow": true, "author": "GabryelPH", "can_mod_post": false, "created_utc": 1777722328.0, "send_replies": true, "parent_id": "t1_ojhitcc", "score": 2, "author_fullname": "t2_3pw5u8ng", "removal_reason": null, "approved_by": null, "mod_note": null, "all_awardings": [], "body": "\u0218i ce a\u021bi rezolvat cu ANAF-ul? Care e solu\u021bia?", "edited": false, "top_awarded_type": null, "author_flair_css_class": null, "name": "t1_ojhl8ba", "is_submitter": true, "downs": 0, "author_flair_richtext": [], "author_patreon_flair": false, "body_html": "&lt;div class=\"md\"&gt;&lt;p&gt;\u0218i ce a\u021bi rezolvat cu ANAF-ul? Care e solu\u021bia?&lt;/p&gt;\n&lt;/div&gt;", "gildings": {}, "collapsed_reason": null, "distinguished": null, "associated_award": null, "stickied": false, "author_premium": false, "can_gild": false, "link_id": "t3_1t10351", "unrepliable_reason": null, "author_flair_text_color": null, "score_hidden": false, "permalink": "/r/RoFiscalitate2/comments/1t10351/poprire_what/ojhl8ba/", "subreddit_type": "public", "locked": false, "report_reasons": null, "created": 1777722328.0, "author_flair_text": null, "treatment_tags": [], "collapsed": false, "subreddit_name_prefixed": "r/RoFiscalitate2", "controversiality": 0, "depth": 1, "author_flair_background_color": null, "collapsed_because_crowd_control": null, "mod_reports": [], "num_reports": null, "ups": 2}}], "before": null}}, "user_reports": [], "saved": false, "id": "ojhitcc", "banned_at_utc": null, "mod_reason_title": null, "gilded": 0, "archived": false, "collapsed_reason_code": null, "no_follow": true, "author": "harubax", "can_mod_post": false, "created_utc": 1777721290.0, "send_replies": true, "parent_id": "t3_1t10351", "score": 3, "author_fullname": "t2_12z3rh", "approved_by": null, "mod_note": null, "all_awardings": [], "collapsed": false, "body": "Am primit \u0219i noi recent, tot printr-un contract cu o firm\u0103 care are ni\u0219te datorii. Practic v\u0103 solicit\u0103 s\u0103 vira\u021bi banii statului \u00een contul datoriei. \u00cen condi\u021biile \u00een care ei au pus poprire \u0219i pe conturile bancare prin sistemul electronic.", "edited": false, "top_awarded_type": null, "author_flair_css_class": null, "name": "t1_ojhitcc", "is_submitter": false, "downs": 0, "author_flair_richtext": [], "author_patreon_flair": false, "body_html": "&lt;div class=\"md\"&gt;&lt;p&gt;Am primit \u0219i noi recent, tot printr-un contract cu o firm\u0103 care are ni\u0219te datorii. Practic v\u0103 solicit\u0103 s\u0103 vira\u021bi banii statului \u00een contul datoriei. \u00cen condi\u021biile \u00een care ei au pus poprire \u0219i pe conturile bancare prin sistemul electronic.&lt;/p&gt;\n&lt;/div&gt;", "removal_reason": null, "collapsed_reason": null, "distinguished": null, "associated_award": null, "stickied": false, "author_premium": false, "can_gild": false, "gildings": {}, "unrepliable_reason": null, "author_flair_text_color": null, "score_hidden": false, "permalink": "/r/RoFiscalitate2/comments/1t10351/poprire_what/ojhitcc/", "subreddit_type": "public", "locked": false, "report_reasons": null, "created": 1777721290.0, "author_flair_text": null, "treatment_tags": [], "link_id": "t3_1t10351", "subreddit_name_prefixed": "r/RoFiscalitate2", "controversiality": 0, "depth": 0, "author_flair_background_color": null, "collapsed_because_crowd_control": null, "mod_reports": [], "num_reports": null, "ups": 3}}, {"kind": "t1", "data": {"subreddit_id": "t5_ap8imo", "approved_at_utc": null, "author_is_blocked": false, "comment_type": null, "awarders": [], "mod_reason_by": null, "banned_by": null, "author_flair_type": "text", "total_awards_received": 0, "subreddit": "RoFiscalitate2", "author_flair_template_id": null, "likes": null, "replies": {"kind": "Listing", "data": {"after": null, "dist": null, "modhash": "", "geo_filter": "", "children": [{"kind": "t1", "data": {"subreddit_id": "t5_ap8imo", "approved_at_utc": null, "author_is_blocked": false, "comment_type": null, "awarders": [], "mod_reason_by": null, "banned_by": null, "author_flair_type": "text", "total_awards_received": 0, "subreddit": "RoFiscalitate2", "author_flair_template_id": null, "likes": null, "replies": {"kind": "Listing", "data": {"after": null, "dist": null, "modhash": "", "geo_filter": "", "children": [{"kind": "t1", "data": {"subreddit_id": "t5_ap8imo", "approved_at_utc": null, "author_is_blocked": false, "comment_type": null, "awarders": [], "mod_reason_by": null, "banned_by": null, "author_flair_type": "text", "total_awards_received": 0, "subreddit": "RoFiscalitate2", "author_flair_template_id": null, "likes": null, "replies": "", "user_reports": [], "saved": false, "id": "ok02e35", "banned_at_utc": null, "mod_reason_title": null, "gilded": 0, "archived": false, "collapsed_reason_code": null, "no_follow": true, "author": "GabryelPH", "can_mod_post": false, "send_replies": true, "parent_id": "t1_ojy4y5g", "score": 2, "author_fullname": "t2_3pw5u8ng", "removal_reason": null, "approved_by": null, "mod_note": null, "all_awardings": [], "body": "Nu pl\u0103tesc nimic \u0219i m\u0103 judec cu el pe clauzele din contract, av\u00e2nd \u00een vedere c\u0103 am pl\u0103tit deja avans. ", "edited": false, "top_awarded_type": null, "downs": 0, "author_flair_css_class": null, "name": "t1_ok02e35", "is_submitter": true, "collapsed": false, "author_flair_richtext": [], "author_patreon_flair": false, "body_html": "&lt;div class=\"md\"&gt;&lt;p&gt;Nu pl\u0103tesc nimic \u0219i m\u0103 judec cu el pe clauzele din contract, av\u00e2nd \u00een vedere c\u0103 am pl\u0103tit deja avans. &lt;/p&gt;\n&lt;/div&gt;", "gildings": {}, "collapsed_reason": null, "distinguished": null, "associated_award": null, "stickied": false, "author_premium": false, "can_gild": false, "link_id": "t3_1t10351", "unrepliable_reason": null, "author_flair_text_color": null, "score_hidden": false, "permalink": "/r/RoFiscalitate2/comments/1t10351/poprire_what/ok02e35/", "subreddit_type": "public", "locked": false, "report_reasons": null, "created": 1777955878.0, "author_flair_text": null, "treatment_tags": [], "created_utc": 1777955878.0, "subreddit_name_prefixed": "r/RoFiscalitate2", "controversiality": 0, "depth": 2, "author_flair_background_color": null, "collapsed_because_crowd_control": null, "mod_reports": [], "num_reports": null, "ups": 2}}], "before": null}}, "user_reports": [], "saved": false, "id": "ojy4y5g", "banned_at_utc": null, "mod_reason_title": null, "gilded": 0, "archived": false, "collapsed_reason_code": null, "no_follow": true, "author": "Sweaty-Relative-7229", "can_mod_post": false, "created_utc": 1777931677.0, "send_replies": true, "parent_id": "t1_oju5dd0", "score": 1, "author_fullname": "t2_103180t7pn", "removal_reason": null, "approved_by": null, "mod_note": null, "all_awardings": [], "body": "si daca nu iti presteaza serviciu pt ca n-are fonduri?", "edited": false, "top_awarded_type": null, "author_flair_css_class": null, "name": "t1_ojy4y5g", "is_submitter": false, "downs": 0, "author_flair_richtext": [], "author_patreon_flair": false, "body_html": "&lt;div class=\"md\"&gt;&lt;p&gt;si daca nu iti presteaza serviciu pt ca n-are fonduri?&lt;/p&gt;\n&lt;/div&gt;", "gildings": {}, "collapsed_reason": null, "distinguished": null, "associated_award": null, "stickied": false, "author_premium": false, "can_gild": false, "link_id": "t3_1t10351", "unrepliable_reason": null, "author_flair_text_color": null, "score_hidden": false, "permalink": "/r/RoFiscalitate2/comments/1t10351/poprire_what/ojy4y5g/", "subreddit_type": "public", "locked": false, "report_reasons": null, "created": 1777931677.0, "author_flair_text": null, "treatment_tags": [], "collapsed": false, "subreddit_name_prefixed": "r/RoFiscalitate2", "controversiality": 0, "depth": 1, "author_flair_background_color": null, "collapsed_because_crowd_control": null, "mod_reports": [], "num_reports": null, "ups": 1}}], "before": null}}, "user_reports": [], "saved": false, "id": "oju5dd0", "banned_at_utc": null, "mod_reason_title": null, "gilded": 0, "archived": false, "collapsed_reason_code": null, "no_follow": true, "author": "GabryelPH", "can_mod_post": false, "created_utc": 1777888251.0, "send_replies": true, "parent_id": "t3_1t10351", "score": 1, "author_fullname": "t2_3pw5u8ng", "approved_by": null, "mod_note": null, "all_awardings": [], "collapsed": false, "body": "A\u0219a cum am promis, revin cu r\u0103spunsul celor de la ANAF. Firma X figureaz\u0103 cu datorii la stat iar toti clien\u021bii contractelor prezente \u0219i viitoare vor primi astfel de popriri astfel \u00eenc\u00e2t \u00eencas\u0103rile se se fac\u0103 la ANAF, nu la firm\u0103. Eu \u00een situa\u021bia asta nu am ce sa fac dar nici nu exista vreun dezavantaj sau risc pentru mine. \n\nExact cum ati scris voi aici pe grup \u0219i pentru care \u021bin s\u0103 v\u0103 mul\u021bumesc! \ud83d\ude4f ", "edited": false, "top_awarded_type": null, "author_flair_css_class": null, "name": "t1_oju5dd0", "is_submitter": true, "downs": 0, "author_flair_richtext": [], "author_patreon_flair": false, "body_html": "&lt;div class=\"md\"&gt;&lt;p&gt;A\u0219a cum am promis, revin cu r\u0103spunsul celor de la ANAF. Firma X figureaz\u0103 cu datorii la stat iar toti clien\u021bii contractelor prezente \u0219i viitoare vor primi astfel de popriri astfel \u00eenc\u00e2t \u00eencas\u0103rile se se fac\u0103 la ANAF, nu la firm\u0103. Eu \u00een situa\u021bia asta nu am ce sa fac dar nici nu exista vreun dezavantaj sau risc pentru mine. &lt;/p&gt;\n\n&lt;p&gt;Exact cum ati scris voi aici pe grup \u0219i pentru care \u021bin s\u0103 v\u0103 mul\u021bumesc! \ud83d\ude4f &lt;/p&gt;\n&lt;/div&gt;", "removal_reason": null, "collapsed_reason": null, "distinguished": null, "associated_award": null, "stickied": false, "author_premium": false, "can_gild": false, "gildings": {}, "unrepliable_reason": null, "author_flair_text_color": null, "score_hidden": false, "permalink": "/r/RoFiscalitate2/comments/1t10351/poprire_what/oju5dd0/", "subreddit_type": "public", "locked": false, "report_reasons": null, "created": 1777888251.0, "author_flair_text": null, "treatment_tags": [], "link_id": "t3_1t10351", "subreddit_name_prefixed": "r/RoFiscalitate2", "controversiality": 0, "depth": 0, "author_flair_background_color": null, "collapsed_because_crowd_control": null, "mod_reports": [], "num_reports": null, "ups": 1}}], "before": null}}]